plugin/__init__.py
plugin/core.py
plugin/discovery.py
plugin/entrypoint.py
plugin/manager.py
plugin/setuptools.py
localstack_plugin_loader-1.1.1.dist-info/LICENSE
localstack_plugin_loader-1.1.1.dist-info/METADATA
localstack_plugin_loader-1.1.1.dist-info/WHEEL
localstack_plugin_loader-1.1.1.dist-info/top_level.txt
localstack_plugin_loader-1.1.1.dist-info/RECORD
