Metadata-Version: 2.1
Name: localstack-plugin-loader
Version: 1.1.1
Summary: The dynamic code loading framework used in LocalStack
Home-page: https://github.com/localstack/localstack-plugin-loader
Author: Thomas Rausch
Author-email: thomas@localstack.cloud
License: Apache License 2.0
Platform: UNKNOWN
Classifier: Development Status :: 5 - Production/Stable
Classifier: License :: OSI Approved :: Apache Software License
Classifier: Operating System :: OS Independent
Classifier: Programming Language :: Python :: 3
Classifier: Programming Language :: Python :: 3.6
Classifier: Programming Language :: Python :: 3.7
Classifier: Programming Language :: Python :: 3.8
Classifier: Programming Language :: Python :: 3.9
Classifier: Topic :: Software Development :: Libraries
Classifier: Topic :: Utilities
Provides-Extra: dev
